who/__init__.py
who/map.py
who/region.py
who/validity.py
who-0.6.dist-info/LICENSE
who-0.6.dist-info/METADATA
who-0.6.dist-info/WHEEL
who-0.6.dist-info/top_level.txt
who-0.6.dist-info/RECORD
